nassl_fork-5.2.0.dist-info/top_level.txt
nassl_fork-5.2.0.dist-info/RECORD
nassl_fork-5.2.0.dist-info/LICENSE.txt
nassl_fork-5.2.0.dist-info/METADATA
nassl_fork-5.2.0.dist-info/WHEEL
nassl/_nassl.cpython-311-x86_64-linux-gnu.so
nassl/ssl_client.py
nassl/ocsp_response.py
nassl/ephemeral_key_info.py
nassl/__init__.py
nassl/cert_chain_verifier.py
nassl/_nassl_legacy.pyi
nassl/legacy_ssl_client.py
nassl/_nassl.pyi
nassl/_nassl_legacy.cpython-311-x86_64-linux-gnu.so
nassl/py.typed
tests/openssl_server/__init__.py
